LICENSE
MANIFEST.in
setup.py
django_lexicon.egg-info/PKG-INFO
django_lexicon.egg-info/SOURCES.txt
django_lexicon.egg-info/dependency_links.txt
django_lexicon.egg-info/requires.txt
django_lexicon.egg-info/top_level.txt
lexicon/__init__.py
lexicon/managers.py
lexicon/models.py