Metadata-Version: 1.1
Name: django-lexicon
Version: 0.1.0
Summary: Abstract classes for defining a lexicon
Home-page: http://cbmi.github.io/django-lexicon/
Author: Byron Ruth
Author-email: b@devel.io
License: BSD
Keywords: lexicon
Platform: UNKNOWN
Classifier: Development Status :: 5 - Production/Stable
Classifier: License :: OSI Approved :: BSD License
Classifier: Programming Language :: Python :: 2.6
Classifier: Programming Language :: Python :: 2.7
Classifier: Framework :: Django
Classifier: Topic :: Internet :: WWW/HTTP
Classifier: Intended Audience :: Developers
Classifier: Intended Audience :: Science/Research
Classifier: Intended Audience :: Healthcare Industry
Classifier: Intended Audience :: Information Technology
